pash/__init__.py
pash/cmds.py
pash/command.py
pash/misc.py
pash/shell.py
pash_cmd-0.0.7.dist-info/LICENSE
pash_cmd-0.0.7.dist-info/METADATA
pash_cmd-0.0.7.dist-info/WHEEL
pash_cmd-0.0.7.dist-info/top_level.txt
pash_cmd-0.0.7.dist-info/RECORD
