Metadata-Version: 2.1
Name: pash-cmd
Version: 0.0.7
Summary: An interactive shell for Python scripts.
Home-page: https://github.com/MattMoony/pash
Author: MattMoony
Author-email: m4ttm00ny@gmail.com
License: UNKNOWN
Download-URL: https://github.com/MattMoony/pash/archive/v_007.tar.gz
Platform: UNKNOWN
Classifier: Programming Language :: Python :: 3
Classifier: License :: OSI Approved :: MIT License
Classifier: Operating System :: OS Independent
Requires-Python: >=3.5
Requires-Dist: colorama (==0.4.4)
